sneact/__init__.py
sneact/_conditions.py
sneact/_loops.py
sneact/_magic_tags.py
sneact/_scopes.py
sneact/_sneact.py
sneact/cond.py
sneact/form.py
sneact/html.py
sneact/loop.py
sneact/web/user.py
sneact-0.1.1.dist-info/WHEEL
sneact-0.1.1.dist-info/METADATA
sneact-0.1.1.dist-info/RECORD
