Metadata-Version: 2.1
Name: sneact
Version: 0.1.1
Summary: Sneact is a python library for building user interfaces
Home-page: https://machineand.me/sneact?f=pypi
License: MIT
Keywords: html,web,drs,sneact,jsless,frontend
Author: Kiselev Nikolay
Author-email: ceo@machineand.me
Requires-Python: >=3.6,<4.0
Classifier: Development Status :: 1 - Planning
Classifier: Intended Audience :: Developers
Classifier: License :: OSI Approved :: MIT License
Classifier: Programming Language :: Python :: 3
Classifier: Programming Language :: Python :: 3.6
Classifier: Programming Language :: Python :: 3.7
Classifier: Programming Language :: Python :: 3.8
Classifier: Programming Language :: Python :: 3.9
Classifier: Topic :: Internet :: WWW/HTTP :: Dynamic Content
Classifier: Topic :: Religion
Classifier: Topic :: Software Development :: Libraries
Classifier: Topic :: Text Processing :: Markup :: HTML
Project-URL: Repository, https://github.com/machineandme/sneact
